serverchan_sdk/__init__.py
serverchan_sdk-1.0.6.dist-info/METADATA
serverchan_sdk-1.0.6.dist-info/WHEEL
serverchan_sdk-1.0.6.dist-info/top_level.txt
serverchan_sdk-1.0.6.dist-info/RECORD
